<!--<?xml version="1.0" encoding="UTF-8"?>-->

<!--<configuration>-->

<!--    &lt;!&ndash; Log Pattern &ndash;&gt;-->
<!--    <property name="LOG_PATTERN"-->
<!--              value="%d{yyyy-MM-dd HH:mm:ss} %-5level %logger{36} - %msg%n"/>-->

<!--    &lt;!&ndash; Log Directory &ndash;&gt;-->
<!--    <property name="LOG_PATH" value="logs"/>-->

<!--    &lt;!&ndash; Rolling File Appender &ndash;&gt;-->
<!--    <appender name="ROLLING_FILE"-->
<!--              class="ch.qos.logback.core.rolling.RollingFileAppender">-->

<!--        &lt;!&ndash; Current active log file &ndash;&gt;-->
<!--        <file>${LOG_PATH}/application.log</file>-->

<!--        &lt;!&ndash; Rolling Policy &ndash;&gt;-->
<!--        <rollingPolicy-->
<!--                class="ch.qos.logback.core.rolling.SizeAndTimeBasedRollingPolicy">-->

<!--            &lt;!&ndash; Archived files &ndash;&gt;-->
<!--            <fileNamePattern>-->
<!--                ${LOG_PATH}/application.%d{yyyy-MM-dd}.%i.log-->
<!--            </fileNamePattern>-->

<!--            &lt;!&ndash; Roll over after 10 MB &ndash;&gt;-->
<!--            <maxFileSize>10MB</maxFileSize>-->

<!--            &lt;!&ndash; Keep logs for 30 days &ndash;&gt;-->
<!--            <maxHistory>30</maxHistory>-->

<!--            &lt;!&ndash; Optional: Total log storage limit &ndash;&gt;-->
<!--            <totalSizeCap>1GB</totalSizeCap>-->

<!--        </rollingPolicy>-->

<!--        <encoder>-->
<!--            <pattern>${LOG_PATTERN}</pattern>-->
<!--        </encoder>-->

<!--    </appender>-->

<!--    &lt;!&ndash; Console Appender &ndash;&gt;-->
<!--    <appender name="CONSOLE"-->
<!--              class="ch.qos.logback.core.ConsoleAppender">-->

<!--        <encoder>-->
<!--            <pattern>${LOG_PATTERN}</pattern>-->
<!--        </encoder>-->

<!--    </appender>-->

<!--    &lt;!&ndash; Application Logging &ndash;&gt;-->
<!--    <root level="INFO">-->
<!--        <appender-ref ref="CONSOLE"/>-->
<!--        <appender-ref ref="ROLLING_FILE"/>-->
<!--    </root>-->

<!--</configuration>-->








<configuration>
    <property name="LOG_PATTERN" value="%d{yyyy-MM-dd HH:mm:ss} %-5level %c{1} - %msg%n" />

    <property name="LOG_PATH" value="logs" />

    <appender name="ROLLING_FILE" class="ch.qos.logback.core.rolling.RollingFileAppender">

        <rollingPolicy class="ch.qos.logback.core.rolling.TimeBasedRollingPolicy">
            <fileNamePattern>${LOG_PATH}/application.%d{yyyy-MM-dd}.%i.log</fileNamePattern>
            <maxHistory>30</maxHistory>
            <timeBasedFileNamingAndTriggeringPolicy class="ch.qos.logback.core.rolling.SizeAndTimeBasedFNATP">
                <maxFileSize>10MB</maxFileSize>
            </timeBasedFileNamingAndTriggeringPolicy>
        </rollingPolicy>

        <encoder>
            <pattern>${LOG_PATTERN}</pattern>
        </encoder>
    </appender>

    <root level="debug">
        <appender-ref ref="ROLLING_FILE" />
    </root>
</configuration>
